{"cameraMode":{"drawMode":0,"name":"Shaded","section":"Shading Mode"},"sceneLighting":true,"audioPlay":false,"sceneViewState":{"showFog":true,"showMaterialUpdate":false,"showSkybox":true,"showFlares":true,"showImageEffects":true,"showParticleSystems":true,"showVisualEffectGraphs":true,"m_FxEnabled":true},"in2DMode":false,"pivot":{"x":395.79998779296877,"y":276.29998779296877,"z":0.0},"rotation":{"x":-0.11949814856052399,"y":-0.2039157599210739,"z":-0.0250295028090477,"w":0.9713917374610901},"size":196.7599639892578,"orthographic":false}